enhanced_adaptive_dbscan/__init__.py
enhanced_adaptive_dbscan/dbscan.py
enhanced_adaptive_dbscan/utils.py
tests/__init__.py
tests/test_dbscan.py
enhanced_adaptive_dbscan-0.1.1.dist-info/License
enhanced_adaptive_dbscan-0.1.1.dist-info/METADATA
enhanced_adaptive_dbscan-0.1.1.dist-info/WHEEL
enhanced_adaptive_dbscan-0.1.1.dist-info/top_level.txt
enhanced_adaptive_dbscan-0.1.1.dist-info/RECORD
