Metadata-Version: 2.1
Name: enhanced_adaptive_dbscan
Version: 0.1.1
Summary: An Enhanced Adaptive DBSCAN clustering algorithm for semiconductor wafer defects.
Home-page: https://github.com/kennedym-ds/enhanced_adaptive_dbscan
Author: Michael Kennedy
Author-email: michael.patrick.kennedy@outlook.ie
Classifier: Programming Language :: Python :: 3
Classifier: License :: OSI Approved :: MIT License
Classifier: Operating System :: OS Independent
Requires-Python: >=3.6
License-File: License
Requires-Dist: numpy
Requires-Dist: scikit-learn
Requires-Dist: plotly
Requires-Dist: joblib
Requires-Dist: pandas
Provides-Extra: dev
Requires-Dist: pytest ; extra == 'dev'
Requires-Dist: sphinx ; extra == 'dev'
Requires-Dist: wheel ; extra == 'dev'
